{"commitInfo":{"timestamp":1753446467751,"operation":"WRITE","operationParameters":{"mode":"Overwrite","partitionBy":"[]"},"readVersion":0,"isolationLevel":"Serializable","isBlindAppend":false,"operationMetrics":{"numFiles":"1","numOutputRows":"5","numOutputBytes":"1439"},"engineInfo":"Apache-Spark/3.5.6 Delta-Lake/3.1.0","txnId":"afd7c3dc-897f-4cce-944d-abff08e17379"}}
{"add":{"path":"part-00000-73d9c946-8f29-407b-b0f9-3ab8ed440ebf-c000.snappy.parquet","partitionValues":{},"size":1439,"modificationTime":1753446466939,"dataChange":true,"stats":"{\"numRecords\":5,\"minValues\":{\"customer_id\":\"1\",\"name\":\"Alice\",\"address\":\"123 Main St\",\"contact_details\":\"alice@example.com\"},\"maxValues\":{\"customer_id\":\"5\",\"name\":\"Eva\",\"address\":\"789 Oak Ave\",\"contact_details\":\"eva@example.com\"},\"nullCount\":{\"customer_id\":0,\"name\":0,\"address\":0,\"contact_details\":0}}"}}
{"remove":{"path":"part-00000-9d41f09d-f8cb-41df-92c3-1c060188399c-c000.snappy.parquet","deletionTimestamp":1753446467727,"dataChange":true,"extendedFileMetadata":true,"partitionValues":{},"size":1439}}
